CODE_OF_CONDUCT.md
LICENSE
models/ProtT5cons_checkpoint.pt
models/VESPA-10LR_Cons_Blsm_Prob.pkl
models/VESPAl-10LR_Cons_Blsm.pkl
vespa/__init__.py
vespa/predict/config.py
vespa/predict/conspred.py
vespa/predict/embedding.py
vespa/predict/logodds.py
vespa/predict/utils.py
vespa/predict/utils_t5.py
vespa/predict/vespa.py
vespa/scripts/__init__.py
vespa/scripts/conspred.py
vespa/scripts/embedding.py
vespa/scripts/logodds.py
vespa/scripts/meta.py
vespa/scripts/vespa_run.py
vespa_effect-1.0.2.dist-info/LICENSE
vespa_effect-1.0.2.dist-info/METADATA
vespa_effect-1.0.2.dist-info/WHEEL
vespa_effect-1.0.2.dist-info/entry_points.txt
vespa_effect-1.0.2.dist-info/RECORD
