Metadata-Version: 2.1
Name: vespa-effect
Version: 1.0.2
Summary: Predictor for single-amino acid variant effects in protein sequences (https://doi.org/10.1007/s00439-021-02411-y)
Home-page: https://github.com/Rostlab/VESPA
License: AGPL-3.0-or-later
Keywords: Embeddings,Protein-Sequences,Machine-Learning,Mutation-Effect
Author: Tobias O
Author-email: tobias.olenyi@tum.de
Requires-Python: >=3.8,<3.11
Classifier: License :: OSI Approved :: GNU Affero General Public License v3 or later (AGPLv3+)
Classifier: Programming Language :: Python :: 3
Classifier: Programming Language :: Python :: 3.8
Classifier: Programming Language :: Python :: 3.9
Classifier: Programming Language :: Python :: 3.10
Requires-Dist: biopython (>=1.79,<2.0)
Requires-Dist: h5py (>=3.4.0,<4.0.0)
Requires-Dist: numpy (>=1.21.2,<2.0.0)
Requires-Dist: pyfaidx (>=0.6.2,<0.7.0)
Requires-Dist: scikit-learn (>=1.2.2,<2.0.0)
Requires-Dist: sentencepiece (>=0.1.96,<0.2.0)
Requires-Dist: torch (>=1.9.0,<2.0.0)
Requires-Dist: tqdm (>=4.62.2,<5.0.0)
Requires-Dist: transformers (>=4.10.2,<5.0.0)
Project-URL: Repository, https://github.com/Rostlab/VESPA
